expected_value/__init__.py
expected_value/expected_value.py
expected_value/outcome1.py
expected_value/probability1.py
expected_value_tb-0.0.1.dist-info/LICENSE
expected_value_tb-0.0.1.dist-info/METADATA
expected_value_tb-0.0.1.dist-info/WHEEL
expected_value_tb-0.0.1.dist-info/top_level.txt
expected_value_tb-0.0.1.dist-info/RECORD
