Metadata-Version: 2.1
Name: expected_value_tb
Version: 0.0.1
Summary: A simple package which calculates the total probability and expected value of the outcome data type
Author-email: Thomas Brumbaugh <thomas.william.brumbaugh@gmail.com>
Project-URL: Homepage, https://github.com/pypa/expected_value_tb
Project-URL: Issues, https://github.com/pypa/expected_value_tb/issues
Classifier: Programming Language :: Python :: 3
Classifier: License :: OSI Approved :: MIT License
Classifier: Operating System :: OS Independent
Requires-Python: >=3.8
License-File: LICENSE
